dirtyfields/__init__.py
dirtyfields/compare.py
dirtyfields/dirtyfields.py
django_filthyfields-1.9.8b3.dist-info/METADATA
django_filthyfields-1.9.8b3.dist-info/WHEEL
django_filthyfields-1.9.8b3.dist-info/licenses/LICENSE
django_filthyfields-1.9.8b3.dist-info/RECORD
